{
  "TableColumns": {
    "Columns": [
      {
        "FieldName": "RegistrationNo",
        "HeaderText": "RegistrationNo",
        "ShortText": "RegistrationNo",
        "Sequence": 1,
        "Visible": true,
        "Width": 100,
        "ResponsivePriority": 1,
        "DataType": 13,
        "MediaFormat": ""
      },
      {
        "FieldName": "VinCode",
        "HeaderText": "VinCode",
        "ShortText": "VinCode",
        "Sequence": 2,
        "Visible": true,
        "Width": 100,
        "ResponsivePriority": 1,
        "DataType": 13,
        "MediaFormat": ""
      },
      {
        "FieldName": "Make",
        "HeaderText": "Make",
        "ShortText": "Make",
        "Sequence": 3,
        "Visible": true,
        "Width": 100,
        "ResponsivePriority": 1,
        "DataType": 13,
        "MediaFormat": ""
      },
      {
        "FieldName": "Model",
        "HeaderText": "Model",
        "ShortText": "Model",
        "Sequence": 4,
        "Visible": true,
        "Width": 100,
        "ResponsivePriority": 1,
        "DataType": 13,
        "MediaFormat": ""
      },
      {
        "FieldName": "Year",
        "HeaderText": "Year",
        "ShortText": "Year",
        "Sequence": 5,
        "Visible": true,
        "Width": 40,
        "ResponsivePriority": 1,
        "DataType": 9,
        "MediaFormat": ""
      },
      {
        "FieldName": "Id",
        "HeaderText": "Key field",
        "ShortText": "Key field",
        "Sequence": 6,
        "Visible": false,
        "Width": 100,
        "ResponsivePriority": 1,
        "DataType": 9,
        "MediaFormat": ""
      },
      {
        "FieldName": "OwnerId",
        "HeaderText": "OwnerId",
        "ShortText": "OwnerId",
        "Sequence": 7,
        "Visible": false,
        "Width": 100,
        "ResponsivePriority": 1,
        "DataType": 9,
        "MediaFormat": ""
      }
    ],
    "Actions": [
      {
        "CssVisual": "btn-primary",
        "CssAction": "edit-btn",
        "DisplayText": "Edit",
        "OnClick": null,
        "IdField": "Id",
        "Area": null,
        "Controller": "Vehicle",
        "Action": "Details",
        "UrlTemplate": "Vehicle/Details/__id__"
      },
      {
        "CssVisual": "btn-danger",
        "CssAction": "edit-btn",
        "DisplayText": "Delete",
        "OnClick": null,
        "IdField": "Id",
        "Area": null,
        "Controller": "Vehicle",
        "Action": "Delete",
        "UrlTemplate": "Vehicle/Delete/__id__"
      }
    ]
  },
  "CondColors": [
    {
      "Sequence": 1,
      "Condition": "Year \u003C currentYear - 10",
      "BackColor": "#ffcccc",
      "FontColor": "#000000"
    },
    {
      "Sequence": 2,
      "Condition": "Year \u003E= currentYear - 5",
      "BackColor": "#b2ff66",
      "FontColor": "#000000"
    }
  ],
  "Version": 1,
  "PageTexts": {
    "OperationName": "Vehicle.Browser",
    "BrowserTabTitle": "Vehicle Browser",
    "ControllerTitle": "Vehicle",
    "ActionTitle": "Index",
    "ActionDescription": "List of Vehicles"
  },
  "Layout": "~/Views/Shared/_Layout.cshtml"
}